fiser_tools/__init__.py
fiser_tools/analytics.py
fiser_tools/dataclean.py
fiser_tools/graphics.py
fiser_tools/machine.py
fiser_tools/misc.py
fiser_tools/transform.py
fiser_tools-2.1.dist-info/LICENSE.txt
fiser_tools-2.1.dist-info/METADATA
fiser_tools-2.1.dist-info/WHEEL
fiser_tools-2.1.dist-info/top_level.txt
fiser_tools-2.1.dist-info/RECORD
