Metadata-Version: 2.1
Name: fiser-tools
Version: 2.1
Summary: Personal DS tools
Home-page: https://github.com/f1se4/fiser_tools
Author: fiser
Author-email: sergi.garcia.munoz@gmail.com
License: MIT
Classifier: Programming Language :: Python :: 3
Classifier: License :: OSI Approved :: MIT License
Classifier: Operating System :: OS Independent
License-File: LICENSE.txt
Requires-Dist: pandas
Requires-Dist: matplotlib
Requires-Dist: seaborn
Requires-Dist: numpy
Requires-Dist: plotly
Requires-Dist: kaleido
Requires-Dist: yellowbrick
Requires-Dist: scikit-learn
Requires-Dist: statsmodels
Requires-Dist: matplotx
Requires-Dist: nbformat
